Metadata-Version: 2.0
Name: amazon-dax-client
Version: 1.0.2
Summary: Amazon DAX Client for Python
Home-page: https://aws.amazon.com/dynamodb/dax/
Author: Amazon Web Services
Author-email: UNKNOWN
License: Apache License 2.0
Platform: UNKNOWN
Classifier: Development Status :: 5 - Production/Stable
Classifier: Intended Audience :: Developers
Classifier: License :: OSI Approved :: Apache Software License
Classifier: Programming Language :: Python
Classifier: Programming Language :: Python :: 2
Classifier: Programming Language :: Python :: 2.7
Classifier: Programming Language :: Python :: 3
Classifier: Programming Language :: Python :: 3.5
Classifier: Programming Language :: Python :: 3.6
Requires-Dist: botocore (~=1.7)
Requires-Dist: six (~=1.11)
Requires-Dist: futures (~=3.2.0)
Requires-Dist: antlr4-python3-runtime (==4.7)
Requires-Dist: antlr4-python2-runtime (==4.7)
